pa_dlna/__init__.py
pa_dlna/config.py
pa_dlna/encoders.py
pa_dlna/http_server.py
pa_dlna/init.py
pa_dlna/pa_dlna.py
pa_dlna/pulseaudio.py
pa_dlna/upnp_cmd.py
pa_dlna/tests/__init__.py
pa_dlna/tests/encoder.py
pa_dlna/tests/gs-16b-1c-44100hz.mp3
pa_dlna/tests/libpulse.py
pa_dlna/tests/parec.py
pa_dlna/tests/streams.py
pa_dlna/tests/test_config.py
pa_dlna/tests/test_http_server.py
pa_dlna/tests/test_init.py
pa_dlna/tests/test_libpulse.py
pa_dlna/tests/test_pa_dlna.py
pa_dlna/tests/test_pulseaudio.py
pa_dlna/tests/test_tracks.py
pa_dlna/upnp/__init__.py
pa_dlna/upnp/network.py
pa_dlna/upnp/upnp.py
pa_dlna/upnp/util.py
pa_dlna/upnp/xml.py
pa_dlna/upnp/tests/__init__.py
pa_dlna/upnp/tests/device_resps.py
pa_dlna/upnp/tests/test_network.py
pa_dlna/upnp/tests/test_upnp.py
pa_dlna/upnp/tests/test_util.py
pa_dlna/upnp/tests/test_xml.py
pa_dlna-1.2.dist-info/entry_points.txt
pa_dlna-1.2.dist-info/licenses/LICENSE
pa_dlna-1.2.dist-info/WHEEL
pa_dlna-1.2.dist-info/METADATA
pa_dlna-1.2.dist-info/RECORD
