Metadata-Version: 2.4
Name: pa-dlna
Version: 1.2
Summary: Forward pulseaudio streams to DLNA devices.
Keywords: pulseaudio,pipewire,DLNA,UPnP,asyncio
Author-email: Xavier de Gaye <xdegaye@gmail.com>
Requires-Python: >=3.8,<4
Classifier: Development Status :: 2 - Pre-Alpha
Classifier: Framework :: AsyncIO
Classifier: License :: OSI Approved :: MIT License
Classifier: Operating System :: Unix
Classifier: Programming Language :: Python :: 3
Classifier: Topic :: Multimedia :: Sound/Audio :: Players
License-File: LICENSE
Requires-Dist: psutil
Requires-Dist: libpulse >=0.7
Project-URL: Changelog, https://pa-dlna.readthedocs.io/en/stable/history.html
Project-URL: Documentation, https://pa-dlna.readthedocs.io/en/stable/
Project-URL: Source, https://gitlab.com/xdegaye/pa-dlna
